azim/__init__.py
azim/lark/__init__.py
azim/lark/lark.py
azim/py.typed
azim-0.1.1.dist-info/WHEEL
azim-0.1.1.dist-info/METADATA
azim-0.1.1.dist-info/RECORD
