Metadata-Version: 2.3
Name: azim
Version: 0.1.1
Summary: Python IM(Instant Messaging) Chat Libs
Keywords: im,chat,libs,sdk,lark,telegram,discord,slack
Author: hhglory
Author-email: hhglory <hhglory@outlook.com>
Requires-Dist: lark-oapi>=1.4.22
Requires-Dist: loguru>=0.7.3
Requires-Python: >=3.12
